rhessys_calibrater/__init__.py
rhessys_calibrater/example_step1.py
rhessys_calibrater/rhessys_calibrater_utils.py
rhessys_calibrater-0.0.2.dist-info/METADATA
rhessys_calibrater-0.0.2.dist-info/WHEEL
rhessys_calibrater-0.0.2.dist-info/licenses/LICENSE
rhessys_calibrater-0.0.2.dist-info/RECORD
