Metadata-Version: 2.1
Name: rhessys_calibrater
Version: 0.0.2
Summary: A package for RHESSys model (https://github.com/RHESSys/RHESSys) calibration using MCMC and k-means clustering
Project-URL: homepage, https://github.com/ruoyu93/rhessys_calibrater
Author-email: Ruoyu Zhang <rz3jr@virginia.edu>
License: Copyright (c) 2018 The Python Packaging Authority
License-File: LICENSE
Classifier: Programming Language :: Python
Classifier: Programming Language :: Python :: 3
Classifier: Programming Language :: Python :: 3 :: Only
Classifier: Programming Language :: Python :: 3.9
Classifier: Programming Language :: Python :: 3.10
Classifier: Programming Language :: Python :: 3.11
Requires-Python: >=3.4
